{
    "work": [
        {
            "title": "Software Developer",
            "company": "Grant Street Group",
            "date": "Mar. 2018 - Present",
            "location": "Pittsburgh, PA",
            "duties": [
                "Newly minted Golang developer for PayHub® services",
                "Perl developer on the PaymentExpress® team",
                "Integrated new state and county clients with PaymentExpress"
            ],
            "icon": "gsg.svg",
            "old": "gsg_old.svg"
        },
        {
            "title": "Software Developer II",
            "company": "Management Science Associates, Inc.",
            "date": "Dec. 2016 – Mar. 2018",
            "location": "Pittsburgh, PA",
            "duties": [
                "Designed and developed a DevOps portal housing a number of monitoring tools using AngularJS, TypeScript, and SCSS using Gulp.js as a build tool",
                "Built REST APIs using Node.js with Express.js to query server, Apache Kafka, Apache ZooKeeper, TestRail, and other miscellaneous data in real-time",
                "Created automated testing suites using Scala, Cucumber, JUnit, and Mockito to expedite the testing phase of the SDLC",
                "Generated automated tasks for monitoring server health and validation of processed files in the ETL pipeline using Bash, Python, and HBase queries",
                "Developed a multi-threaded application used for data quality analysis with Scala, sbt, and Apache Hive SQL",
                "Developed an account tracking tool for weekly status updates using a complex SQL query that reads Apache HBase and Apache Hive tables",
                "Implemented, maintained, and executed build and deployment plans via the Atlassian software stack as a DevOps engineer",
                "Participated in grooming, planning, and daily standups within a Scrum environment",
                "Wrote comprehensive documentation on completed projects denoting usage and process flow",
                "Reviewed daily Linux server logs to monitor development and production servers for potential problems",
                "Carried out 24/7 on-call duties to assess and remedy production issues"
            ],
            "icon": "msa.svg",
            "old": "msa_old.svg"
        },
        {
            "title": "IT Business Analyst Intern",
            "company": "TE Connectivity",
            "date": "May 2016 – Aug. 2016",
            "location": "Harrisburg, PA",
            "duties": [
                "Oversaw a multi-year project that inventories and rationalizes every application used by TE globally along with their associated operating costs, user base, strategic value, etc.",
                "Collaborated with international teams to improve the data acquisition process and analyze the application portfolio data",
                "Designed a prototype dashboard using the D3.js library and CAML Queries to summarize the application portfolio data",
                "Provided quality assurance testing and wrote technical documentation for a web-based application tracker"
            ],
            "icon": "te.svg",
            "old": "amp_inc.svg"
        }
    ],
    "skills": {
        "frontend": {
            "name": "Frontend",
            "list": [
                "JavaScript", "jQuery", "AngularJS", "HTML", "CSS", "SCSS", "TypeScript", "Django", "PHP"
            ]
        },
        "backend": {
            "name": "Backend",
            "list": [
                "Perl", "Golang", "Node.js", "Scala", "Python", "Java", "C"
            ]
        },
        "testing": {
            "name": "Testing Frameworks",
            "list": [
                "JUnit", "Mockito", "Cucumber", "Selenium"
            ]
        },
        "misc": {
            "name": "Misc. Technical Skills",
            "list": [
                "Linux", "Bash", "Git", "MySQL", "HBase"
            ]
        },
        "other": {
            "name": "Other Skills",
            "list": [
                "Scrum Methodology", "Atlassian Stack", "Adobe Creative Suite", "Microsoft Office"
            ]
        }
    },
    "education": [
        {
            "school": "University of Pittsburgh",
            "location": "Pittsburgh, PA",
            "years": [2015, 2016],
            "type": "B.S.",
            "major": "Computer Science",
            "logo": "pitt.svg",
            "seal": "pitt_seal.svg"
        },
        {
            "school": "Shippensburg University",
            "location": "Shippensburg, PA",
            "years": [2012, 2013],
            "type": "M.S.",
            "major": "Biology",
            "logo": "ship.svg",
            "seal": "ship_seal.svg"
        },
        {
            "school": "University of Pittsburgh",
            "location": "Pittsburgh, PA",
            "years": [2008, 2012],
            "type": "B.S.",
            "major": "Biological Sciences",
            "minor": "Chemistry",
            "logo": "pitt.svg",
            "seal": "pitt_seal.svg"
        }
    ],
    "unrelated": [
        {
            "title": "Certified Nursing Assistant",
            "company": "Twin Oaks Health and Rehabilitation Center",
            "date": "Apr. 2014 – Jun. 2014",
            "location": "Palmyra, PA",
            "duties": [
                "Provided healthcare for geriatric patients in both a long-term and acute rehab facility",
                "Assisted in bathing, skin care, oral care, feeding, physical therapy, etc of patients",
                "Documented healthcare provided and medical details of patients",
                "Aided nurses with more advanced patient care"
            ],
            "icon": "twin_oaks.svg"
        },
        {
            "title": "Quality Control Technician (temp.)",
            "company": "The Warrell Corporation",
            "date": "Dec. 2013 – Jan. 2014",
            "location": "Camp Hill, PA",
            "duties": [
                "Analyzed food production lines to maintain compliance with GMP standards",
                "Performed numerous checks on products including mass, oxygen levels, packaging, etc.",
                "Documented daily checks with statistical analysis to ensure factory requirements",
                "Improved functionality of company’s Excel spreadsheets regarding graphical and statistical analysis"
            ],
            "icon": "warrell.svg"
        }
    ]
}
